{
  "en_name": "Kampong Cham",
  "districts": [
    {
      "en_name": "Batheay",
      "kh_name": "បាធាយ",
      "communes": [
      ]
    },
    {
      "en_name": "Chamkar Leu",
      "kh_name": "ចំការលើ",
      "communes": [
      ]
    },
    {
      "en_name": "Cheung Prey",
      "kh_name": "ជើងព្រៃ",
      "communes": [
      ]
    },
    {
      "en_name": "Krong Kampong Cham",
      "kh_name": "ក្រុងកំពង់ចាម",
      "communes": [
      ]
    },
    {
      "en_name": "Kampong Siem",
      "kh_name": "កំពង់សៀម",
      "communes": [
      ]
    },
    {
      "en_name": "Kang Meas",
      "kh_name": "កងមាស",
      "communes": [
      ]
    },
    {
      "en_name": "Kaoh Soutin",
      "kh_name": "កោះសូទិន",
      "communes": [
      ]
    },
    {
      "en_name": "Prey Chhor",
      "kh_name": "ព្រៃឈរ",
      "communes": [
      ]
    },
    {
      "en_name": "Srei Santhor",
      "kh_name": "ស្រីសន្ធរ",
      "communes": [
      ]
    },
    {
      "en_name": "Stueng Trang",
      "kh_name": "ស្ទឹងត្រង់",
      "communes": [
      ]
    }
  ]
}
